jdNBTExplorer/AboutWindow.py
jdNBTExplorer/EditWindow.py
jdNBTExplorer/Environment.py
jdNBTExplorer/Functions.py
jdNBTExplorer/Languages.py
jdNBTExplorer/Logo.png
jdNBTExplorer/MainWindow.py
jdNBTExplorer/OpenDirectoryTypeDialog.py
jdNBTExplorer/Settings.py
jdNBTExplorer/SettingsWindow.py
jdNBTExplorer/TagItem.py
jdNBTExplorer/TreeWidget.py
jdNBTExplorer/__init__.py
jdNBTExplorer/__main__.py
jdNBTExplorer/version.txt
jdNBTExplorer/data/changelog.html
jdNBTExplorer/data/translators.json
jdNBTExplorer/translations/jdNBTExplorer_de.qm
jdNBTExplorer/translations/jdNBTExplorer_nl.qm
jdNBTExplorer/ui_compiled/AboutWindow.py
jdNBTExplorer/ui_compiled/EditWindow.py
jdNBTExplorer/ui_compiled/MainWindow.py
jdNBTExplorer/ui_compiled/OpenDirectoryTypeDialog.py
jdNBTExplorer/ui_compiled/SettingsWindow.py
jdNBTExplorer/ui_compiled/__init__.py
jdnbtexplorer-3.0.dist-info/licenses/LICENSE
jdnbtexplorer-3.0.dist-info/METADATA
jdnbtexplorer-3.0.dist-info/WHEEL
jdnbtexplorer-3.0.dist-info/entry_points.txt
jdnbtexplorer-3.0.dist-info/top_level.txt
jdnbtexplorer-3.0.dist-info/RECORD
