Metadata-Version: 2.4
Name: jdNBTExplorer
Version: 3.0
Summary: A simple program for creating animated Images
Author-email: JakobDev <jakobdev@gmx.de>
License-Expression: GPL-3.0-only
Project-URL: Source, https://codeberg.org/JakobDev/jdNBTExplorer
Project-URL: Issues, https://codeberg.org/JakobDev/jdNBTExplorer/issues
Project-URL: Translate, https://translate.codeberg.org/projects/jdNBTExplorer
Project-URL: Donation, https://ko-fi.com/jakobdev
Keywords: JakobDev,PyQt,PyQt6,Minecraft,NBT,English,German
Classifier: Development Status :: 5 - Production/Stable
Classifier: Intended Audience :: Developers
Classifier: Intended Audience :: End Users/Desktop
Classifier: Environment :: Other Environment
Classifier: Environment :: X11 Applications :: Qt
Classifier: Natural Language :: English
Classifier: Natural Language :: German
Classifier: Operating System :: OS Independent
Classifier: Operating System :: POSIX
Classifier: Operating System :: POSIX :: BSD
Classifier: Operating System :: POSIX :: Linux
Classifier: Operating System :: MacOS :: MacOS X
Classifier: Operating System :: Microsoft :: Windows
Classifier: Programming Language :: Python :: 3
Classifier: Programming Language :: Python :: 3.10
Classifier: Programming Language :: Python :: 3.11
Classifier: Programming Language :: Python :: 3.12
Classifier: Programming Language :: Python :: 3.13
Classifier: Programming Language :: Python :: 3 :: Only
Classifier: Programming Language :: Python :: Implementation :: CPython
Requires-Python: >=3.10
License-File: LICENSE
Requires-Dist: PyQt6
Requires-Dist: nbt
Dynamic: license-file
